bin/__init__.py
bin/sinterbot.py
sinterbot/__init__.py
sinterbot/algorithms.py
sinterbot/config.py
sinterbot/sinterconf.py
sinterbot/smtpconf.py
sinterbot-0.1.1.dist-info/METADATA
sinterbot-0.1.1.dist-info/WHEEL
sinterbot-0.1.1.dist-info/entry_points.txt
sinterbot-0.1.1.dist-info/top_level.txt
sinterbot-0.1.1.dist-info/RECORD
