Metadata-Version: 2.1
Name: sinterbot
Version: 0.1.1
Summary: A program to manage secret santa assignments.
Home-page: https://github.com/cristoper/sinterbot
Author: cristoper
Author-email: chris@catswhisker.xyz
License: license.txt
Platform: UNKNOWN
Classifier: Development Status :: 4 - Beta
Classifier: License :: OSI Approved :: MIT License
Classifier: Programming Language :: Python :: 3.5
Requires-Python: >=3.4
Provides-Extra: dev
Requires-Dist: mypy ; extra == 'dev'
